unvtray/__main__.py
unvtray/common.py
unvtray/launch.py
unvtray/ping.py
unvtray/server.py
unvtray/servers.py
unvtray/tray.py
unvtray/assets/FreeMonoBold.otf
unvtray/assets/unvanquished.png
unvtray-0.2.1.dist-info/LICENSE.txt
unvtray-0.2.1.dist-info/METADATA
unvtray-0.2.1.dist-info/WHEEL
unvtray-0.2.1.dist-info/entry_points.txt
unvtray-0.2.1.dist-info/top_level.txt
unvtray-0.2.1.dist-info/RECORD
