Metadata-Version: 2.1
Name: unvtray
Version: 0.2.1
Summary: Unvanquished Tray
Author-email: Maximilian Stahlberg <viech@unvanquished.net>
License: GPL-3.0-or-later
Project-URL: Homepage, https://unvanquished.net
Project-URL: Repository, https://github.com/Unvanquished/unvanquished-tray-browser
Keywords: unvanquished
Classifier: License :: OSI Approved :: GNU General Public License v3 or later (GPLv3+)
Classifier: Programming Language :: Python :: 3
Classifier: Topic :: Games/Entertainment :: First Person Shooters
Classifier: Topic :: Games/Entertainment :: Real Time Strategy
Requires-Python: >=3.3
License-File: LICENSE.txt
Requires-Dist: pillow
Requires-Dist: pystray
